FDLib/__init__.py
FDLib/types.py
FDLib/utils.py
FDLib/factory/__init__.py
FDLib/factory/base.py
FDLib/factory/fd_ele.py
FDLib/factory/fd_lib.py
FDLib/lib/__init__.py
FDLib/lib/_shape.py
FDLib/lib/arc.py
FDLib/lib/path.py
FDLib/lib/polygon.py
FDLib/lib/polygon_with_hole.py
FDLib/lib/rectangle.py
farady_python-0.1.3.dist-info/licenses/LICENSE
farady_python-0.1.3.dist-info/METADATA
farady_python-0.1.3.dist-info/WHEEL
farady_python-0.1.3.dist-info/top_level.txt
farady_python-0.1.3.dist-info/RECORD
