Metadata-Version: 2.4
Name: farady-python
Version: 0.1.3
Summary: Farady Python Library
Home-page: https://github.com/Tinger-X/Farady-Python
Author: Tinger
Author-email: email@tingerx.com
Classifier: Programming Language :: Python :: 3
Classifier: License :: OSI Approved :: MIT License
Classifier: Operating System :: OS Independent
Requires-Python: >=3.6
License-File: LICENSE
Requires-Dist: matplotlib
Dynamic: author
Dynamic: author-email
Dynamic: classifier
Dynamic: description
Dynamic: description-content-type
Dynamic: home-page
Dynamic: license-file
Dynamic: requires-dist
Dynamic: requires-python
Dynamic: summary
